[
  {
    "name": "Arts Department",
    "class": "Arts",
    "semester": "Semester-1",
    "id": 1
  },
  {
    "name": "Arts Department",
    "class": "Arts",
    "semester": "Semester-2",
    "id": 2
  },
  {
    "name": "Arts Department",
    "class": "Arts",
    "semester": "Semester-3",
    "id": 3
  },
  {
    "name": "Arts Department",
    "class": "Arts",
    "semester": "Semester-4",
    "id": 4
  },
  {
    "name": "Chemistry Department",
    "class": "Chemistry",
    "semester": "Semester-1",
    "id": 5
  },
  {
    "name": "Chemistry Department",
    "class": "Chemistry",
    "semester": "Semester-2",
    "id": 6
  },
  {
    "name": "Chemistry Department",
    "class": "Chemistry",
    "semester": "Semester-3",
    "id": 7
  },
  {
    "name": "Chemistry Department",
    "class": "Chemistry",
    "semester": "Semester-4",
    "id": 8
  },
  {
    "name": "Chemistry Department",
    "class": "Chemistry",
    "semester": "Semester-5",
    "id": 9
  },
  {
    "name": "Chemistry Department",
    "class": "Chemistry",
    "semester": "Semester-6",
    "id": 10
  },
  {
    "name": "DCSA Department",
    "class": "MCA",
    "semester": "Semester-1",
    "id": 11
  },

  {
    "name": "DCSA Department",
    "class": "MCA",
    "semester": "Semester-2",
    "id": 12
  },
  {
    "name": "DCSA Department",
    "class": "MCA",
    "semester": "Semester-3",
    "id": 13,
    "navigate": "DepartmentScreen"
  },
  {
    "name": "Dcsa Department",
    "class": "MCA",
    "semester": "Semester-4",
    "id": 14
  },
  {
    "name": "Dcsa Department",
    "class": "MCA",
    "semester": "Semester-5",
    "id": 15
  },
  {
    "name": "Dcsa Department",
    "class": "MCA",
    "semester": "Semester-6",
    "id": 16
  },
  {
    "name": "Dcsa Department",
    "class": "Msc",
    "semester": "Semester-1",
    "id": 17
  },
  {
    "name": "Dcsa Department",
    "class": "Msc",
    "semester": "Semester-2",
    "id": 18
  },
  {
    "name": "Dcsa Department",
    "class": "Msc",
    "semester": "Semester-3",
    "id": 19
  },
  {
    "name": "Dcsa Department",
    "class": "Msc",
    "semester": "Sem-4",
    "id": 20
  },
  {
    "name": "Dcsa Department",
    "class": "PGDCA",
    "semester": "Sem-1",
    "id": 21
  },
  {
    "name": "Dcsa Department",
    "class": "PGDCA",
    "semester": "Sem-2",
    "id": 22
  },
  {
    "name": "English Department",
    "class": "English",
    "semester": "Sem-1",
    "id": 23
  },
  {
    "name": "English Department",
    "class": "English",
    "semester": "Sem-2",
    "id": 24
  },
  {
    "name": "English Department",
    "class": "English",
    "semester": "Sem-3",
    "id": 25
  },
  {
    "name": "English Department",
    "class": "English",
    "semester": "Sem-4",
    "id": 26
  },
  {
    "name": "English Department",
    "class": "English",
    "semester": "Sem-5",
    "id": 27
  },
  {
    "name": "English Department",
    "class": "English",
    "semester": "Sem-6",
    "id": 28
  },
  {
    "name": "Hindi Department",
    "class": "Hindi",
    "semester": "Sem-1",
    "id": 29
  },
  {
    "name": "Hindi Department",
    "class": "Hindi",
    "semester": "Sem-2",
    "id": 30
  },
  {
    "name": "Hindi Department",
    "class": "Hindi",
    "semester": "Sem-3",
    "id": 31
  },
  {
    "name": "Hindi Department",
    "class": "Hindi",
    "semester": "Sem-4",
    "id": 32
  },
  {
    "name": "Hindi Department",
    "class": "Hindi",
    "semester": "Sem-5",
    "id": 33
  },
  {
    "name": "Hindi Department",
    "class": "Hindi",
    "semester": "Sem-6",
    "id": 34
  },
  {
    "name": "Maths Department",
    "class": "Maths",
    "semester": "Sem-1",
    "id": 35
  },
  {
    "name": "Maths Department",
    "class": "Maths",
    "semester": "Sem-2",
    "id": 36
  },
  {
    "name": "Maths Department",
    "class": "Maths",
    "semester": "Sem-3",
    "id": 37
  },
  {
    "name": "Maths Department",
    "class": "Maths",
    "semester": "Sem-4",
    "id": 38
  },
  {
    "name": "Panjabi Department",
    "class": "Panjabi",
    "semester": "Sem-1",
    "id": 39
  },
  {
    "name": "Panjabi Department",
    "class": "Panjabi",
    "semester": "Sem-2",
    "id": 40
  },
  {
    "name": "Panjabi Department",
    "class": "Panjabi",
    "semester": "Sem-3",
    "id": 41
  },
  {
    "name": "Panjabi Department",
    "class": "Panjabi",
    "semester": "Sem-4",
    "id": 42
  },
  {
    "name": "Panjabi Department",
    "class": "Panjabi",
    "semester": "Sem-5",
    "id": 43
  },
  {
    "name": "Panjabi Department",
    "class": "Panjabi",
    "semester": "Sem-6",
    "id": 44
  },
  {
    "name": "Pharmaceutical Sciences Department",
    "class": "Pharmaceutical",
    "semester": "Sem-1",
    "id": 45
  },
  {
    "name": "Pharmaceutical Sciences Department",
    "class": "Pharmaceutical",
    "semester": "Sem-2",
    "id": 46
  },
  {
    "name": "Pharmaceutical Sciences Department",
    "class": "Pharmaceutical",
    "semester": "Sem-3",
    "id": 47
  },
  {
    "name": "Pharmaceutical Sciences Department",
    "class": "Pharmaceutical",
    "semester": "Sem-4",
    "id": 48
  }

]
